overlay_audio/__init__.py
overlay_audio/aovervid.py
aovervid-0.1.dist-info/LICENSE
aovervid-0.1.dist-info/METADATA
aovervid-0.1.dist-info/WHEEL
aovervid-0.1.dist-info/entry_points.txt
aovervid-0.1.dist-info/top_level.txt
aovervid-0.1.dist-info/RECORD
