Metadata-Version: 2.1
Name: aovervid
Version: 0.1
Summary: Скрипт для замены и наложения аудио на видео.
Home-page: https://twitter.com/Lanaev0li
Author: Avinion
Author-email: shizofrin@gmail.com
License: 
Classifier: Programming Language :: Python :: 3
Classifier: License :: Other/Proprietary License
Classifier: Operating System :: OS Independent
Requires-Python: >=3.6
License-File: LICENSE
